tcwindprofile/__init__.py
tcwindprofile/plot_windprofile.py
tcwindprofile/pressure_profile.py
tcwindprofile/tc_outer_radius_estimate.py
tcwindprofile/tc_outer_windprofile.py
tcwindprofile/tc_pmin_estimatefromR34kt.py
tcwindprofile/tc_rmax_estimatefromR34kt.py
tcwindprofile/windprofile.py
tcwindprofile/windprofile_all.py
tcwindprofile-2.1.1.dist-info/licenses/LICENSE
tcwindprofile-2.1.1.dist-info/METADATA
tcwindprofile-2.1.1.dist-info/WHEEL
tcwindprofile-2.1.1.dist-info/top_level.txt
tcwindprofile-2.1.1.dist-info/RECORD
