Metadata-Version: 2.4
Name: tcwindprofile
Version: 2.1.1
Summary: Create a fast and robust radial profile of the tropical cyclone rotating wind and pressure field from inputs Vmax, R34kt, latitude, translation speed, and environmental pressure
Home-page: https://github.com/drchavas/tcwindprofile
Author: Dan Chavas
Author-email: drchavas@gmail.com
License: MIT
Classifier: Programming Language :: Python :: 3
Classifier: License :: OSI Approved :: MIT License
Classifier: Operating System :: OS Independent
Requires-Python: >=3.6
License-File: LICENSE
Dynamic: author
Dynamic: author-email
Dynamic: classifier
Dynamic: description
Dynamic: description-content-type
Dynamic: home-page
Dynamic: license
Dynamic: license-file
Dynamic: requires-python
Dynamic: summary
